setup.cfg
setup.py
libtrust/__init__.py
libtrust/ec_key.py
libtrust/hash.py
libtrust/jsonsign.py
libtrust/key.py
libtrust/rsa_key.py
libtrust/util.py
libtrust_py.egg-info/PKG-INFO
libtrust_py.egg-info/SOURCES.txt
libtrust_py.egg-info/dependency_links.txt
libtrust_py.egg-info/not-zip-safe
libtrust_py.egg-info/requires.txt
libtrust_py.egg-info/top_level.txt