Metadata-Version: 1.0
Name: libtrust-py
Version: 0.1
Summary: Integrate docker/libtrust with python.
Home-page: https://github.com/realityone/libtrust-py
Author: UNKNOWN
Author-email: UNKNOWN
License: UNKNOWN
Platform: UNKNOWN
